gethonis/__init__.py
gethonis-0.0.5.dist-info/licenses/LICENSE
gethonis-0.0.5.dist-info/METADATA
gethonis-0.0.5.dist-info/WHEEL
gethonis-0.0.5.dist-info/top_level.txt
gethonis-0.0.5.dist-info/RECORD
