Metadata-Version: 2.4
Name: gethonis
Version: 0.0.5
Summary: A lightweight Python library to interact with the Gethonis API. Gethonis combines the best of OpenAI's ChatGPT responses with Grok's capabilities for an enhanced conversational experience.
Author-email: Lucian-Florin <lucianfl0rin@protonmail.com>
License: 
Classifier: Programming Language :: Python :: 3
Classifier: License :: OSI Approved :: MIT License
Classifier: Operating System :: OS Independent
Requires-Python: >=3.7
License-File: LICENSE
Requires-Dist: requests
Dynamic: license-file
